MANIFEST.in
account_chart.xml
account_chart_template.xml
account_tax_code_template.xml
account_taxes.xml
account_types.xml
fiscal_position_templates.xml
l10n_chart_pt_wizard.xml
setup.py
./__init__.py
./__openerp__.py
i18n/pt.po
openerp_l10n_pt.egg-info/PKG-INFO
openerp_l10n_pt.egg-info/SOURCES.txt
openerp_l10n_pt.egg-info/dependency_links.txt
openerp_l10n_pt.egg-info/requires.txt
openerp_l10n_pt.egg-info/top_level.txt